fastdeploy/__init__.py
fastdeploy_gpu_python-0.1.0.dist-info/LICENSE
fastdeploy_gpu_python-0.1.0.dist-info/METADATA
fastdeploy_gpu_python-0.1.0.dist-info/WHEEL
fastdeploy_gpu_python-0.1.0.dist-info/top_level.txt
fastdeploy_gpu_python-0.1.0.dist-info/RECORD
