Metadata-Version: 2.1
Name: fastdeploy-gpu-python
Version: 0.1.0
Summary: FastDeploy is a toolkit to deploy deeplearning models.
Home-page: https://github.com/PaddlePaddle/FastDeploy
Author: FastDeploy
Author-email: fastdeploy@baidu.com
License: Apache 2.0
Platform: UNKNOWN
Classifier: Programming Language :: Python :: 3
Classifier: License :: OSI Approved :: Apache Software License
Classifier: Operating System :: OS Independent
License-File: LICENSE
